LICENSE
giant_news/__init__.py
giant_news/admin.py
giant_news/apps.py
giant_news/cms_apps.py
giant_news/cms_plugins.py
giant_news/feeds.py
giant_news/forms.py
giant_news/migrations/0001_initial.py
giant_news/migrations/0002_relatedarticlecardplugin_relatedarticleplugin.py
giant_news/migrations/0003_alter_article_content.py
giant_news/migrations/0004_auto_20220601_0915.py
giant_news/migrations/0005_auto_20220912_0459.py
giant_news/migrations/0006_alter_article_author_alter_article_category_and_more.py
giant_news/migrations/0007_relatedarticleplugin_title.py
giant_news/migrations/0008_author_external_url.py
giant_news/migrations/__init__.py
giant_news/models/__init__.py
giant_news/models/article.py
giant_news/models/plugin.py
giant_news/sitemaps.py
giant_news/templates/base.html
giant_news/templates/news/detail.html
giant_news/templates/news/index.html
giant_news/templates/plugins/related_articles/container.html
giant_news/templates/plugins/related_articles/item.html
giant_news/tests/__init__.py
giant_news/tests/test_cms_apps.py
giant_news/tests/test_feeds.py
giant_news/tests/test_forms.py
giant_news/tests/test_models.py
giant_news/tests/test_views.py
giant_news/tests/urls.py
giant_news/urls.py
giant_news/views.py
giant_news-1.3.2.dist-info/LICENSE
giant_news-1.3.2.dist-info/METADATA
giant_news-1.3.2.dist-info/WHEEL
giant_news-1.3.2.dist-info/RECORD
