Metadata-Version: 2.1
Name: giant-news
Version: 1.3.2
Summary: A small reusable package that adds a News app to a project
Home-page: https://github.com/giantmade/giant-news
License: MIT
Keywords: giant_news,app
Author: Will-Hoey
Author-email: will.hoey@giantdigital.co.uk
Requires-Python: >=3.9,<4.0
Classifier: Environment :: Console
Classifier: License :: OSI Approved :: MIT License
Classifier: Operating System :: OS Independent
Classifier: Programming Language :: Python :: 3
Classifier: Programming Language :: Python :: 3.9
Classifier: Programming Language :: Python :: 3.10
Classifier: Programming Language :: Python :: 3.11
Classifier: Topic :: Software Development :: Documentation
Classifier: Topic :: Software Development :: Libraries :: Python Modules
Requires-Dist: django-filer
Requires-Dist: giant-mixins
Requires-Dist: swapper (>=1.3.0,<2.0.0)
Project-URL: Repository, https://github.com/giantmade/giant-news
